{
    "version": "0.2.0",
    "architecture": {
        "32bit": {
            "url": "https://github.com/kha7iq/pingme/releases/download/v0.2.0/pingme_Windows_i386.zip",
            "bin": [
                "pingme.exe"
            ],
            "hash": "e5d8e00e8aac0336082a38f2021b969cc35264c5911fd72353ae687a8e6b06d5"
        },
        "64bit": {
            "url": "https://github.com/kha7iq/pingme/releases/download/v0.2.0/pingme_Windows_x86_64.zip",
            "bin": [
                "pingme.exe"
            ],
            "hash": "b478045d3dcb8805cf6e2cad9550de747b9ac17459b31e05ba13d1c7d4eff061"
        }
    },
    "homepage": "https://pingme.lmno.pk",
    "license": "MIT",
    "description": "PingMe is a CLI tool which provides the ability to send messages or alerts to multiple messaging platforms."
}