{
    "version": "0.1.3",
    "architecture": {
        "32bit": {
            "url": "https://github.com/kha7iq/subvars/releases/download/v0.1.3/subvars_Windows_i386.zip",
            "bin": [
                "subvars.exe"
            ],
            "hash": "9b1371b4ac628f8a49e00fec3415f394d687de43d48461d538ae6f459490cbb6"
        },
        "64bit": {
            "url": "https://github.com/kha7iq/subvars/releases/download/v0.1.3/subvars_Windows_x86_64.zip",
            "bin": [
                "subvars.exe"
            ],
            "hash": "fc9566eaf3a18061734ac619f581946d81e56bc97244d95e1bc07b5d80e33d48"
        }
    },
    "homepage": "https://subvars.lmno.pk",
    "license": "MIT",
    "description": "Substitute environment variables from command line in config files defined as go template format."
}